<?xml version="1.0" encoding="UTF-8"?>
<templates xml:space="preserve">
  <t t-name="mail.client_action">
    <div class="o_mail_chat">
     <div class="o_mail_chat_sidebar"/>
     <div class="o_mail_chat_content">
       <t t-if="widget.notification_bar">
         <div class="o_mail_annoying_notification_bar" style="display:none;">
           <span class="o_mail_request_permission">Odoo needs your permission to <a href="#"> enable desktop notifications</a>.</span>
           <span class="fa fa-close"/>
         </div>
       </t>
     </div>
    </div>
  </t>
</templates>
